testdummypackage/__init__.py
testdummypackage/arithmetic.py
testdummypackage/geometry.py
sherwood-0.2.0.dist-info/LICENSE
sherwood-0.2.0.dist-info/METADATA
sherwood-0.2.0.dist-info/WHEEL
sherwood-0.2.0.dist-info/top_level.txt
sherwood-0.2.0.dist-info/RECORD
