Metadata-Version: 2.1
Name: sherwood
Version: 0.2.0
Summary: Yet Another Math Library
Home-page: https://github.com/fbasurto/yaml
Author: Fernando Basurto Echevarria
Author-email: fernando.basurto.echevarria@gmail.com
License: MIT
Classifier: Programming Language :: Python :: 3
Classifier: License :: OSI Approved :: MIT License
Classifier: Operating System :: OS Independent
Requires-Python: >=3.6
License-File: LICENSE
